crimson/study_ast/__init__.py
crimson/study_ast/convert.py
crimson/study_ast/dev_tool.py
crimson/study_ast/edit_code.py
crimson/study_ast/extract.py
crimson/study_ast/specs.py
crimson_study_ast-0.1.2.dist-info/LICENSE
crimson_study_ast-0.1.2.dist-info/METADATA
crimson_study_ast-0.1.2.dist-info/WHEEL
crimson_study_ast-0.1.2.dist-info/top_level.txt
crimson_study_ast-0.1.2.dist-info/RECORD
