Metadata-Version: 2.1
Name: crimson-study-ast
Version: 0.1.2
Summary: Study Ast.
Author-email: Sisung Kim <sisung.kim1@gmail.com>
Project-URL: Homepage, https://github.com/crimson206/study-ast
Project-URL: Bug Tracker, https://github.com/crimson206/study-ast/issues
Classifier: Programming Language :: Python :: 3
Classifier: Intended Audience :: Developers
Classifier: Topic :: Software Development :: Build Tools
Classifier: License :: OSI Approved :: MIT License
Classifier: Operating System :: OS Independent
Requires-Python: >=3.9
License-File: LICENSE
Requires-Dist: pydantic
Requires-Dist: crimson-data-class
